feateng/__init__.py
feateng/main.py
feateng/utils.py
feateng-0.3.0.dist-info/licenses/LICENSE
feateng-0.3.0.dist-info/METADATA
feateng-0.3.0.dist-info/WHEEL
feateng-0.3.0.dist-info/top_level.txt
feateng-0.3.0.dist-info/RECORD
